libhum/__init__.py
libhum/analysis.py
libhum/io.py
libhum/main.py
libhum/match.kernel
libhum/match.py
libhum/match_score_regressor.pickle
libhum/merge.py
libhum/types.py
libhum-1.1.5.dist-info/LICENSE
libhum-1.1.5.dist-info/METADATA
libhum-1.1.5.dist-info/WHEEL
libhum-1.1.5.dist-info/entry_points.txt
libhum-1.1.5.dist-info/top_level.txt
libhum-1.1.5.dist-info/RECORD
