Metadata-Version: 2.1
Name: libhum
Version: 1.1.5
Summary: Libhum is a Python GPU-accelerated library to extract and compare Electricity Frequency Signals (ENF)
Author-email: Raphael Javaux <raphael@noisycamp.com>
License:                    GNU LESSER GENERAL PUBLIC LICENSE
Project-URL: Homepage, https://github.com/RaphaelJ/libhum/
Project-URL: Issues, https://github.com/RaphaelJ/libhum/issues
Classifier: License :: OSI Approved :: GNU Lesser General Public License v3 or later (LGPLv3+)
Classifier: Programming Language :: Python :: 3
Classifier: Environment :: GPU
Classifier: Operating System :: OS Independent
Classifier: Topic :: Multimedia :: Sound/Audio :: Analysis
Classifier: Topic :: Scientific/Engineering :: Information Analysis
Requires-Python: >=3.10
License-File: LICENSE
Requires-Dist: attrs>=23.1.0
Requires-Dist: audiofile>=1.2.1
Requires-Dist: lz4>=4.3.2
Requires-Dist: matplotlib>=3.7.1
Requires-Dist: numpy>=1.24.3
Requires-Dist: requests>=2.28.2
Requires-Dist: scikit-learn>=1.3.2
Requires-Dist: scipy>=1.10.1
Requires-Dist: sortedcontainers>=2.4.0
Provides-Extra: opencl
Requires-Dist: pyopencl>=2022.3.1; extra == "opencl"
Provides-Extra: cuda
Requires-Dist: pycuda>=2022.2.2; extra == "cuda"
